AUTHORS
LICENSE.txt
MANIFEST.in
README.rst
cuisine_postgresql.py
setup.py
cuisine_postgresql.egg-info/PKG-INFO
cuisine_postgresql.egg-info/SOURCES.txt
cuisine_postgresql.egg-info/dependency_links.txt
cuisine_postgresql.egg-info/requires.txt
cuisine_postgresql.egg-info/top_level.txt