Metadata-Version: 1.1
Name: cuisine-postgresql
Version: 0.2.1
Summary: Cuisine methods for PosgreSQL
Home-page: http://github.com/muhuk/cuisine-postgresql
Author: Atamert Ölçgen
Author-email: muhuk@muhuk.com
License: Copyright (c) 2006, Atamert Ölçgen (http://www.muhuk.com)
